Classfile /Users/mac/code/geek-course/src/main/java/com/github/shaylau/geekCourse/week01/HelloByteCode.class
  Last modified Feb 28, 2022; size 499 bytes
  MD5 checksum 80bed64cd0a77b0d563306fd1c6550a8
  Compiled from "HelloByteCode.java"
public class com.github.shaylau.geekCourse.week01.HelloByteCode
  minor version: 0
  major version: 52
  flags: ACC_PUBLIC, ACC_SUPER
Constant pool:
   #1 = Methodref          #4.#19         // java/lang/Object."<init>":()V
   #2 = Class              #20            // com/github/shaylau/geekCourse/week01/HelloByteCode
   #3 = Methodref          #2.#19         // com/github/shaylau/geekCourse/week01/HelloByteCode."<init>":()V
   #4 = Class              #21            // java/lang/Object
   #5 = Utf8               <init>
   #6 = Utf8               ()V
   #7 = Utf8               Code
   #8 = Utf8               LineNumberTable
   #9 = Utf8               LocalVariableTable
  #10 = Utf8               this
  #11 = Utf8               Lcom/github/shaylau/geekCourse/week01/HelloByteCode;
  #12 = Utf8               main
  #13 = Utf8               ([Ljava/lang/String;)V
  #14 = Utf8               args
  #15 = Utf8               [Ljava/lang/String;
  #16 = Utf8               helloByteCode
  #17 = Utf8               SourceFile
  #18 = Utf8               HelloByteCode.java
  #19 = NameAndType        #5:#6          // "<init>":()V
  #20 = Utf8               com/github/shaylau/geekCourse/week01/HelloByteCode
  #21 = Utf8               java/lang/Object
{
  public com.github.shaylau.geekCourse.week01.HelloByteCode();
    descriptor: ()V
    flags: ACC_PUBLIC
    Code:
      stack=1, locals=1, args_size=1
         0: aload_0
         1: invokespecial #1                  // Method java/lang/Object."<init>":()V
         4: return
      LineNumberTable:
        line 3: 0
      LocalVariableTable:
        Start  Length  Slot  Name   Signature
            0       5     0  this   Lcom/github/shaylau/geekCourse/week01/HelloByteCode;

  public static void main(java.lang.String[]);
    descriptor: ([Ljava/lang/String;)V
    flags: ACC_PUBLIC, ACC_STATIC
    Code:
      stack=2, locals=2, args_size=1
         0: new           #2                  // class com/github/shaylau/geekCourse/week01/HelloByteCode
         3: dup
         4: invokespecial #3                  // Method "<init>":()V
         7: astore_1
         8: return
      LineNumberTable:
        line 6: 0
        line 7: 8
      LocalVariableTable:
        Start  Length  Slot  Name   Signature
            0       9     0  args   [Ljava/lang/String;
            8       1     1 helloByteCode   Lcom/github/shaylau/geekCourse/week01/HelloByteCode;
}
SourceFile: "HelloByteCode.java"
